Metadata-Version: 2.4
Name: ogplc
Version: 0.0.0
Summary: High-Level Database Client for OpenGov Permitting & Licensing
Home-page: https://github.com/officeofperformancemanagement/ogplc
Download-URL: https://github.com/officeofperformancemanagement/ogplc/tarball/download
Author: Daniel J. Dufour
Author-email: daniel.j.dufour@gmail.com
Keywords: data,python
Classifier: Development Status :: 4 - Beta
Classifier: Programming Language :: Python :: 3
Classifier: License :: CC0 1.0 Universal (CC0 1.0) Public Domain Dedication
Classifier: Operating System :: OS Independent
License-File: LICENSE
Requires-Dist: pyodbc
Dynamic: author
Dynamic: author-email
Dynamic: classifier
Dynamic: description
Dynamic: description-content-type
Dynamic: download-url
Dynamic: home-page
Dynamic: keywords
Dynamic: license-file
Dynamic: requires-dist
Dynamic: summary
